pycarwings3/__init__.py
pycarwings3/pycarwings3.py
pycarwings3/responses.py
pycarwings3-0.7.14.dist-info/licenses/LICENSE
pycarwings3-0.7.14.dist-info/METADATA
pycarwings3-0.7.14.dist-info/WHEEL
pycarwings3-0.7.14.dist-info/top_level.txt
pycarwings3-0.7.14.dist-info/RECORD
