Metadata-Version: 2.4
Name: pycarwings3
Version: 0.7.14
Summary: Python library for interacting with the Nissan Leaf Carwings telematics service
Home-page: https://github.com/ev-freaks/pycarwings3
Author: Remus Lazar
Author-email: remus@ev-freaks.com
License: Apache Software License
Keywords: nissan leaf carwings nissan+you
Classifier: Development Status :: 4 - Beta
Classifier: Intended Audience :: Developers
Classifier: License :: OSI Approved :: Apache Software License
Classifier: Programming Language :: Python :: 3 :: Only
License-File: LICENSE
Requires-Dist: PyYAML
Requires-Dist: iso8601
Requires-Dist: pycryptodome
Requires-Dist: aiohttp~=3.10
Requires-Dist: pytz
Requires-Dist: asyncio
Dynamic: author
Dynamic: author-email
Dynamic: classifier
Dynamic: description
Dynamic: description-content-type
Dynamic: home-page
Dynamic: keywords
Dynamic: license
Dynamic: license-file
Dynamic: requires-dist
Dynamic: summary
